divr_diagnosis/__init__.py
divr_diagnosis/diagnosis.py
divr_diagnosis/diagnosis_map.py
divr_diagnosis/diagnosis_maps.py
divr_diagnosis/diagnosis_maps/Benba_2017.yml
divr_diagnosis/diagnosis_maps/CaRLab_2025.yml
divr_diagnosis/diagnosis_maps/Compton_2022.yml
divr_diagnosis/diagnosis_maps/Cordeiro_2015.yml
divr_diagnosis/diagnosis_maps/FEMH_2018.yml
divr_diagnosis/diagnosis_maps/Firdos_2016.yml
divr_diagnosis/diagnosis_maps/Kim_2024.yml
divr_diagnosis/diagnosis_maps/Sztaho_2018.yml
divr_diagnosis/diagnosis_maps/Tsui_2018.yml
divr_diagnosis/diagnosis_maps/USVAC_2025.yml
divr_diagnosis/diagnosis_maps/Zaim_2023.yml
divr_diagnosis/diagnosis_maps/daSilvaMoura_2024.yml
divr_diagnosis/diagnosis_maps/deMoraesLimaMarinus_2013.yml
divr_diagnosis-0.1.2.dist-info/METADATA
divr_diagnosis-0.1.2.dist-info/WHEEL
divr_diagnosis-0.1.2.dist-info/top_level.txt
divr_diagnosis-0.1.2.dist-info/RECORD
