Metadata-Version: 2.2
Name: divr-diagnosis
Version: 0.1.2
Summary: Toolkit to standardize voice disorder diagnostic labels
Home-page: https://github.com/ComputationalAudioResearchLab/divr-diagnosis
Author: Computational Audio Research Lab
License: MIT
Keywords: ML Audio Features,ML,Disordered Voice Features,Research
Classifier: Development Status :: 4 - Beta
Classifier: Intended Audience :: Science/Research
Classifier: License :: OSI Approved :: MIT License
Classifier: Operating System :: OS Independent
Classifier: Topic :: Scientific/Engineering
Requires-Dist: PyYAML>=6.0.1
Dynamic: author
Dynamic: classifier
Dynamic: description
Dynamic: description-content-type
Dynamic: home-page
Dynamic: keywords
Dynamic: license
Dynamic: requires-dist
Dynamic: summary
